ExploitSearch/__init__.py
ExploitSearch/cvesearch.py
exploitsearch-0.1.dist-info/LICENSE
exploitsearch-0.1.dist-info/METADATA
exploitsearch-0.1.dist-info/WHEEL
exploitsearch-0.1.dist-info/top_level.txt
exploitsearch-0.1.dist-info/RECORD
