Metadata-Version: 2.1
Name: exploitsearch
Version: 0.1
Summary: Python package for exploit search by cve-id
Home-page: https://github.com/nimish38/ExploitSearch
Author: Nimish Shinde
Author-email: nimish.v.shinde60@gmail.com
License: UNKNOWN
Platform: UNKNOWN
Classifier: Programming Language :: Python :: 3
Classifier: License :: OSI Approved :: MIT License
Classifier: Operating System :: OS Independent
Requires-Python: >=3.6
Requires-Dist: requests (~=2.24.0)
